trueapi/__init__.py
truectl-0.0.1.dist-info/LICENSE
truectl-0.0.1.dist-info/METADATA
truectl-0.0.1.dist-info/WHEEL
truectl-0.0.1.dist-info/top_level.txt
truectl-0.0.1.dist-info/RECORD
